flask_bloggy/__init__.py
flask_bloggy/blueprint.py
flask_bloggy/cli.py
flask_bloggy/db.py
flask_bloggy/ddbstream_processor.py
flask_bloggy/event_processor.py
flask_bloggy/events.py
flask_bloggy/extension.py
flask_bloggy/filters.py
flask_bloggy/models.py
flask_bloggy/s3.py
flask_bloggy/tracing.py
flask_bloggy/util.py
flask_bloggy/templates/layout.html
flask_bloggy/templates/bloggy/macros.html
flask_bloggy/templates/bloggy/post.html
flask_bloggy/templates/bloggy/posts.html
flask_bloggy-0.1.1.dist-info/LICENSE
flask_bloggy-0.1.1.dist-info/METADATA
flask_bloggy-0.1.1.dist-info/WHEEL
flask_bloggy-0.1.1.dist-info/entry_points.txt
flask_bloggy-0.1.1.dist-info/top_level.txt
flask_bloggy-0.1.1.dist-info/RECORD
