Metadata-Version: 2.1
Name: flask-bloggy
Version: 0.1.1
Summary: A simple but fast blog extension for Flask.
License: MIT License
Project-URL: Homepage, https://github.com/andycaine/flask-bloggy
Project-URL: Documentation, https://github.com/andycaine/flask-bloggy?tab=readme-ov-file
Project-URL: Repository, https://github.com/andycaine/flask-bloggy.git
Keywords: flask,blog
License-File: LICENSE
Requires-Dist: click
Requires-Dist: flask
Requires-Dist: Markdown
Requires-Dist: pillow
Requires-Dist: opentelemetry-api
Requires-Dist: nsst
Requires-Dist: web-paging[flask]
Provides-Extra: boto3
Requires-Dist: boto3; extra == "boto3"
